aptiviti_ingestor/__init__.py
aptiviti_ingestion_pipe-1.0.1.dist-info/LICENSE
aptiviti_ingestion_pipe-1.0.1.dist-info/METADATA
aptiviti_ingestion_pipe-1.0.1.dist-info/WHEEL
aptiviti_ingestion_pipe-1.0.1.dist-info/top_level.txt
aptiviti_ingestion_pipe-1.0.1.dist-info/RECORD
