Metadata-Version: 2.1
Name: aptiviti-ingestion-pipe
Version: 1.0.1
Summary: Aptiviti wrapper for data ingestion provider
Home-page: https://github.com/aptiviti/aptiviti-ingestion-pipe
Author: Daniel Fredriksen
Author-email: df@etr.ai
License: AGPLv3
Platform: UNKNOWN
